<amendment session="113" chamber="s" number="23" updated="2013-03-01T04:54:59-05:00">
  <amends type="s" number="16" sequence=""/>
  <status datetime="2013-02-28">offered</status>
  <sponsor id="300025"/>
  <offered datetime="2013-02-28"/>
  <description>Purpose will be available when the amendment is proposed for consideration.  See  Congressional Record for text.</description>
  <purpose>Purpose will be available when the amendment is proposed for consideration.  See  Congressional Record for text.</purpose>
  <actions/>
</amendment>
